{
  "id": "others/docusaurus-default-doc/index",
  "title": "Docusaurus default document",
  "description": "",
  "source": "@site/docs/others/docusaurus-default-doc/index.mdx",
  "sourceDirName": "others/docusaurus-default-doc",
  "slug": "/others/docusaurus-default-doc/",
  "permalink": "/docs/others/docusaurus-default-doc/",
  "draft": false,
  "unlisted": false,
  "tags": [],
  "version": "current",
  "frontMatter": {},
  "sidebar": "tutorialSidebar",
  "previous": {
    "title": "Other",
    "permalink": "/docs/others/"
  },
  "next": {
    "title": "Create a Page",
    "permalink": "/docs/others/docusaurus-default-doc/create-a-page"
  }
}